featurescope/__init__.py
featurescope/_version.py
featurescope/apply.py
featurescope/featurizer.py
featurescope-0.0.2.dist-info/METADATA
featurescope-0.0.2.dist-info/WHEEL
featurescope-0.0.2.dist-info/top_level.txt
featurescope-0.0.2.dist-info/RECORD
